networking_ale_omniswitch-1.0.1.data/data/etc/neutron/plugins/ml2/omniswitch_network_plugin.ini
networking_ale_omniswitch-1.0.1.dist-info/METADATA
networking_ale_omniswitch-1.0.1.dist-info/WHEEL
networking_ale_omniswitch-1.0.1.dist-info/entry_points.txt
networking_ale_omniswitch-1.0.1.dist-info/metadata.json
networking_ale_omniswitch-1.0.1.dist-info/RECORD
networking_ale_omniswitch-1.0.1.dist-info/top_level.txt
networking_ale_omniswitch-1.0.1.dist-info/DESCRIPTION.rst
networking_ale_omniswitch-1.0.1.dist-info/pbr.json
networking_ale_omniswitch/omniswitch_telnet_driver.py
networking_ale_omniswitch/omniswitch_restful_driver.py
networking_ale_omniswitch/consumer.py
networking_ale_omniswitch/omniswitch_mechanism_driver.py
networking_ale_omniswitch/omniswitch_constants.py
networking_ale_omniswitch/__init__.py
networking_ale_omniswitch/config.py
networking_ale_omniswitch/omniswitch_device_plugin.py
networking_ale_omniswitch/tests/base.py
networking_ale_omniswitch/tests/test_networking_ale_omniswitch.py
networking_ale_omniswitch/tests/__init__.py
networking_ale_omniswitch/tests/unit/omniswitch_telnet_driver_test.py
networking_ale_omniswitch/tests/unit/test_omniswitch_restful_driver.py
networking_ale_omniswitch/tests/unit/omniswitch_restful_driver_test.py
networking_ale_omniswitch/tests/unit/__init__.py
networking_ale_omniswitch/tests/unit/test_omniswitch_telnet_driver.py
networking_ale_omniswitch/tests/unit/test_omniswitch_device_plugin.py
