Metadata-Version: 2.0
Name: networking-ale-omniswitch
Version: 1.0.1
Summary: Alatel-Lucent Enterprise Omniswitch Networking Driver
Home-page: https://github.com/openstack/networking-ale-omniswitch
Author: Vadivel Poonathan
Author-email: vadivel.poonathan@alcatel-lucent.com
License: UNKNOWN
Platform: UNKNOWN
Classifier: Environment :: OpenStack
Classifier: Intended Audience :: Information Technology
Classifier: Intended Audience :: System Administrators
Classifier: License :: OSI Approved :: Apache Software License
Classifier: Operating System :: POSIX :: Linux
Classifier: Programming Language :: Python
Classifier: Programming Language :: Python :: 2
Classifier: Programming Language :: Python :: 2.7
Requires-Dist: pbr (<2.0,>=1.4)
Requires-Dist: Babel (>=1.3)
Requires-Dist: eventlet (>=0.17.4)
Requires-Dist: oslo.config (>=1.11.0)
